cataloger/__init__.py
cataloger/commands.py
cataloger/defaults.py
cataloger/main.py
cataloger/processor.py
cataloger/version.py
cataloger/templates/final_check.tmpl
cataloger/templates/final_create.tmpl
cataloger-1.0.0rc5.dist-info/METADATA
cataloger-1.0.0rc5.dist-info/WHEEL
cataloger-1.0.0rc5.dist-info/entry_points.txt
cataloger-1.0.0rc5.dist-info/top_level.txt
cataloger-1.0.0rc5.dist-info/RECORD
