Metadata-Version: 2.4
Name: cataloger
Version: 1.0.0rc5
Summary: Simple to use tools to create and check directory contents - ideal for integrity checking
Home-page: https://upload.pypi.org/legacy/
Author: Tony Flury
Author-email: anthony.flury@btinternet.com
License: MIT License
Keywords: Development,Deployment,Integrity Checking
Classifier: Development Status :: 5 - Production/Stable
Classifier: Intended Audience :: Developers
Classifier: Topic :: Software Development :: Quality Assurance
Classifier: Programming Language :: Python :: 3.12
Requires-Dist: Click
Requires-Dist: six
Requires-Dist: templatelite
Provides-Extra: dev
Provides-Extra: test
Requires-Dist: pyfakefs; extra == "test"
Dynamic: author
Dynamic: author-email
Dynamic: classifier
Dynamic: description
Dynamic: home-page
Dynamic: keywords
Dynamic: license
Dynamic: provides-extra
Dynamic: requires-dist
Dynamic: summary
